nimbus_utils/__init__.py
nimbus_utils/archive.py
nimbus_utils/baseconv.py
nimbus_utils/crypto.py
nimbus_utils/dateparse.py
nimbus_utils/datetime_safe.py
nimbus_utils/decorator.py
nimbus_utils/duration.py
nimbus_utils/encoding.py
nimbus_utils/filter.py
nimbus_utils/functional.py
nimbus_utils/hashable.py
nimbus_utils/itercompat.py
nimbus_utils/lru_cache.py
nimbus_utils/menu.py
nimbus_utils/numberformat.py
nimbus_utils/safestring.py
nimbus_utils/timezone.py
nimbus_utils/urlparse.py
nimbus_utils/utils.py
nimbus_utils/xmlutils.py
nimbus_utils/encrypt/__init__.py
nimbus_utils/encrypt/aes/__init__.py
nimbus_utils/encrypt/aes/base.py
nimbus_utils/encrypt/aes/cbc_cryptor.py
nimbus_utils/encrypt/aes/eax_cryptor.py
nimbus_utils/encrypt/aes/ecb_cryptor.py
nimbus_utils/encrypt/aes/fernet_cryptor.py
nimbus_utils/encrypt/aes/utils.py
nimbus_utils/encrypt/rsa/__init__.py
nimbus_utils/encrypt/rsa/cryptor.py
nimbus_utils/nimbus_jwt/__init__.py
nimbus_utils/nimbus_jwt/api_jws.py
nimbus_utils/nimbus_jwt/api_jwt.py
nimbus_utils-1.5.6.dist-info/LICENSE.md
nimbus_utils-1.5.6.dist-info/METADATA
nimbus_utils-1.5.6.dist-info/WHEEL
nimbus_utils-1.5.6.dist-info/top_level.txt
nimbus_utils-1.5.6.dist-info/RECORD
